django_admin_generator/__about__.py
django_admin_generator/__init__.py
django_admin_generator/management/__init__.py
django_admin_generator/management/commands/__init__.py
django_admin_generator/management/commands/admin_generator.py
test_project/__init__.py
test_project/manage.py
test_project/settings.py
test_project/test_commands.py
test_project/urls.py
test_project/wsgi.py
test_project/test_app/__init__.py
test_project/test_app/models.py
test_project/test_app/tests.py
test_project/test_app/views.py
django_admin_generator_blokz-1.1.3.dist-info/METADATA
django_admin_generator_blokz-1.1.3.dist-info/WHEEL
django_admin_generator_blokz-1.1.3.dist-info/top_level.txt
django_admin_generator_blokz-1.1.3.dist-info/RECORD
