Metadata-Version: 2.1
Name: django-admin-generator-blokz
Version: 1.1.3
Summary: Django Admin Generator is a management command to automatically generate a Django `admin.py` file for given apps/models.
Home-page: https://github.com/blok-z/django-admin-generator/
Author: Mohamed Abdulaziz
Author-email: mo@blok-z.com
License: BSD
Platform: UNKNOWN
Classifier: Development Status :: 5 - Production/Stable
Classifier: Environment :: Web Environment
Classifier: Intended Audience :: Developers
Classifier: License :: OSI Approved :: BSD License
Classifier: Natural Language :: English
Classifier: Programming Language :: Python :: 3.6
Classifier: Programming Language :: Python :: 3.7
Classifier: Programming Language :: Python :: 3.8
Requires-Dist: django-utils2 (>=2.5.0)
Requires-Dist: six
Provides-Extra: docs
Requires-Dist: django (>=1.11) ; extra == 'docs'
Requires-Dist: mock ; extra == 'docs'
Requires-Dist: sphinx (>=1.6.0) ; extra == 'docs'
Provides-Extra: tests
Requires-Dist: pytest ; extra == 'tests'
Requires-Dist: pytest-cache ; extra == 'tests'
Requires-Dist: pytest-cov ; extra == 'tests'
Requires-Dist: pytest-django ; extra == 'tests'
Requires-Dist: pytest-flakes ; extra == 'tests'
Requires-Dist: pytest-pep8 ; extra == 'tests'
